[{
    "author": "Christine Ebel",
    "last name": "Ebel",
    "idRef": "idref03372329X",
    "coauthors": [
        "Tim Schulte",
        "Cecilia Mikaelsson",
        "Audrey Beaussart",
        "Alexey Kikhney",
        "Maya Deshmukh",
        "Sebastian Wolniak",
        "Anuj Pathak",
        "Jonas Löfling",
        "Federico Fogolari",
        "Birgitta Henriques-Normark",
        "Yves F. Dufrêne",
        "Dmitri Svergun",
        "Per-Åke Nygren",
        "Adnane Achour",
        "Yves F. Dufrêne"
    ],
    "defaultTitle": "The BR domain of PsrP interacts with extracellular DNA to promote bacterial aggregation; structural insights into pneumococcal biofilm formation",
    "venue": "Scientific Reports",
    "duplicId": 0
}]